{
    "key": "group_605a7a8f95ac7",
    "title": "Block : Testimonials",
    "fields": [
        {
            "key": "field_605a7a8f9f90e",
            "label": "Layout",
            "name": "",
            "type": "tab",
            "instructions": "",
            "required": 0,
            "conditional_logic": 0,
            "wrapper": {
                "width": "",
                "class": "",
                "id": ""
            },
            "acfe_permissions": "",
            "placement": "top",
            "endpoint": 0
        },
        {
            "key": "field_605a7a8f9f916",
            "label": "Layout",
            "name": "testimonials_layout",
            "type": "flexible_content",
            "instructions": "",
            "required": 0,
            "conditional_logic": 0,
            "wrapper": {
                "width": "",
                "class": "hide-label hide-acf-controls",
                "id": ""
            },
            "acfe_permissions": "",
            "acfe_flexible_advanced": 1,
            "acfe_flexible_stylised_button": 1,
            "acfe_flexible_layouts_templates": 0,
            "acfe_flexible_layouts_placeholder": 1,
            "acfe_flexible_layouts_thumbnails": 1,
            "acfe_flexible_layouts_settings": 0,
            "acfe_flexible_async": [
                "title",
                "layout"
            ],
            "acfe_flexible_add_actions": [
                "title",
                "copy",
                "lock",
                "close"
            ],
            "acfe_flexible_remove_button": [],
            "acfe_flexible_modal_edit": {
                "acfe_flexible_modal_edit_enabled": "1",
                "acfe_flexible_modal_edit_size": "large"
            },
            "acfe_flexible_modal": {
                "acfe_flexible_modal_enabled": "1",
                "acfe_flexible_modal_title": "Select Layout",
                "acfe_flexible_modal_size": "full",
                "acfe_flexible_modal_col": "4",
                "acfe_flexible_modal_categories": "0"
            },
            "layouts": {
                "layout_5f025b8c375e2": {
                    "key": "layout_5f025b8c375e2",
                    "name": "testimonials_1",
                    "label": "Testimonials 1",
                    "display": "block",
                    "sub_fields": [
                        {
                            "key": "field_605a7a9014c6b",
                            "label": "Testimonials",
                            "name": "testimonials",
                            "type": "clone",
                            "instructions": "",
                            "required": 0,
                            "conditional_logic": 0,
                            "wrapper": {
                                "width": "",
                                "class": "",
                                "id": ""
                            },
                            "acfe_permissions": "",
                            "clone": [
                                "group_5f025cb612228"
                            ],
                            "display": "seamless",
                            "layout": "",
                            "prefix_label": 0,
                            "prefix_name": 0,
                            "acfe_clone_modal": 0
                        }
                    ],
                    "min": "",
                    "max": "",
                    "acfe_flexible_thumbnail": "",
                    "acfe_flexible_render_template": false,
                    "acfe_flexible_render_style": false,
                    "acfe_flexible_render_script": false,
                    "acfe_flexible_settings": false,
                    "acfe_flexible_settings_size": "medium",
                    "acfe_flexible_modal_edit_size": false,
                    "acfe_flexible_category": false
                },
                "layout_5f025d82eaf16": {
                    "key": "layout_5f025d82eaf16",
                    "name": "testimonials_2",
                    "label": "Testimonials 2",
                    "display": "block",
                    "sub_fields": [
                        {
                            "key": "field_605a7a9014c76",
                            "label": "Testimonials",
                            "name": "testimonials",
                            "type": "clone",
                            "instructions": "",
                            "required": 0,
                            "conditional_logic": 0,
                            "wrapper": {
                                "width": "",
                                "class": "",
                                "id": ""
                            },
                            "acfe_permissions": "",
                            "clone": [
                                "group_5f025cb612228"
                            ],
                            "display": "seamless",
                            "layout": "",
                            "prefix_label": 0,
                            "prefix_name": 0,
                            "acfe_clone_modal": 0
                        },
                        {
                            "key": "field_605a7a9014c83",
                            "label": "Logos",
                            "name": "logos",
                            "type": "clone",
                            "instructions": "",
                            "required": 0,
                            "conditional_logic": 0,
                            "wrapper": {
                                "width": "",
                                "class": "",
                                "id": ""
                            },
                            "acfe_permissions": "",
                            "clone": [
                                "group_5fe119e6b86f0"
                            ],
                            "display": "seamless",
                            "layout": "block",
                            "prefix_label": 0,
                            "prefix_name": 0,
                            "acfe_settings": ""
                        }
                    ],
                    "min": "",
                    "max": "",
                    "acfe_flexible_thumbnail": "",
                    "acfe_flexible_render_template": false,
                    "acfe_flexible_render_style": false,
                    "acfe_flexible_render_script": false,
                    "acfe_flexible_settings": false,
                    "acfe_flexible_settings_size": "medium",
                    "acfe_flexible_modal_edit_size": false,
                    "acfe_flexible_category": false
                },
                "layout_5f025dc1eaf1b": {
                    "key": "layout_5f025dc1eaf1b",
                    "name": "testimonials_3",
                    "label": "Testimonials 3",
                    "display": "block",
                    "sub_fields": [
                        {
                            "key": "field_605a7a9014c8f",
                            "label": "Testimonials",
                            "name": "testimonials",
                            "type": "clone",
                            "instructions": "",
                            "required": 0,
                            "conditional_logic": 0,
                            "wrapper": {
                                "width": "",
                                "class": "",
                                "id": ""
                            },
                            "acfe_permissions": "",
                            "clone": [
                                "group_5f025cb612228"
                            ],
                            "display": "seamless",
                            "layout": "",
                            "prefix_label": 0,
                            "prefix_name": 0,
                            "acfe_clone_modal": 0
                        },
                        {
                            "key": "field_605a7a9014c9b",
                            "label": "Heading",
                            "name": "heading",
                            "type": "clone",
                            "instructions": "",
                            "required": 0,
                            "conditional_logic": 0,
                            "wrapper": {
                                "width": "",
                                "class": "",
                                "id": ""
                            },
                            "acfe_permissions": "",
                            "clone": [
                                "group_5f0df4956b0c7"
                            ],
                            "display": "seamless",
                            "layout": "block",
                            "prefix_label": 0,
                            "prefix_name": 0,
                            "acfe_clone_modal": 0
                        }
                    ],
                    "min": "",
                    "max": "",
                    "acfe_flexible_thumbnail": "",
                    "acfe_flexible_render_template": false,
                    "acfe_flexible_render_style": false,
                    "acfe_flexible_render_script": false,
                    "acfe_flexible_settings": false,
                    "acfe_flexible_settings_size": "medium",
                    "acfe_flexible_modal_edit_size": false,
                    "acfe_flexible_category": false
                },
                "layout_5f025df1eaf21": {
                    "key": "layout_5f025df1eaf21",
                    "name": "testimonials_4",
                    "label": "Testimonials 4",
                    "display": "block",
                    "sub_fields": [
                        {
                            "key": "field_605a7a9014ca8",
                            "label": "Testimonials",
                            "name": "testimonials",
                            "type": "clone",
                            "instructions": "",
                            "required": 0,
                            "conditional_logic": 0,
                            "wrapper": {
                                "width": "",
                                "class": "",
                                "id": ""
                            },
                            "acfe_permissions": "",
                            "clone": [
                                "group_5f025cb612228"
                            ],
                            "display": "seamless",
                            "layout": "",
                            "prefix_label": 0,
                            "prefix_name": 0,
                            "acfe_clone_modal": 0
                        }
                    ],
                    "min": "",
                    "max": "",
                    "acfe_flexible_thumbnail": "",
                    "acfe_flexible_render_template": false,
                    "acfe_flexible_render_style": false,
                    "acfe_flexible_render_script": false,
                    "acfe_flexible_settings": false,
                    "acfe_flexible_settings_size": "medium",
                    "acfe_flexible_modal_edit_size": false,
                    "acfe_flexible_category": false
                },
                "layout_5f025e05eaf26": {
                    "key": "layout_5f025e05eaf26",
                    "name": "testimonials_5",
                    "label": "Testimonials 5",
                    "display": "block",
                    "sub_fields": [
                        {
                            "key": "field_605a7a9014cb5",
                            "label": "Testimonials",
                            "name": "testimonials",
                            "type": "clone",
                            "instructions": "",
                            "required": 0,
                            "conditional_logic": 0,
                            "wrapper": {
                                "width": "",
                                "class": "",
                                "id": ""
                            },
                            "acfe_permissions": "",
                            "clone": [
                                "group_5f025cb612228"
                            ],
                            "display": "seamless",
                            "layout": "",
                            "prefix_label": 0,
                            "prefix_name": 0,
                            "acfe_clone_modal": 0
                        }
                    ],
                    "min": "",
                    "max": "",
                    "acfe_flexible_thumbnail": "",
                    "acfe_flexible_render_template": false,
                    "acfe_flexible_render_style": false,
                    "acfe_flexible_render_script": false,
                    "acfe_flexible_settings": false,
                    "acfe_flexible_settings_size": "medium",
                    "acfe_flexible_modal_edit_size": false,
                    "acfe_flexible_category": false
                },
                "layout_5f025e0aeaf29": {
                    "key": "layout_5f025e0aeaf29",
                    "name": "testimonials_6",
                    "label": "Testimonials 6",
                    "display": "block",
                    "sub_fields": [
                        {
                            "key": "field_605a7a9014cc2",
                            "label": "Testimonials",
                            "name": "testimonials",
                            "type": "clone",
                            "instructions": "",
                            "required": 0,
                            "conditional_logic": 0,
                            "wrapper": {
                                "width": "",
                                "class": "",
                                "id": ""
                            },
                            "acfe_permissions": "",
                            "clone": [
                                "group_5f025cb612228"
                            ],
                            "display": "seamless",
                            "layout": "block",
                            "prefix_label": 0,
                            "prefix_name": 0,
                            "acfe_clone_modal": 0
                        }
                    ],
                    "min": "",
                    "max": "",
                    "acfe_flexible_thumbnail": "",
                    "acfe_flexible_render_template": false,
                    "acfe_flexible_render_style": false,
                    "acfe_flexible_render_script": false,
                    "acfe_flexible_settings": false,
                    "acfe_flexible_settings_size": "medium",
                    "acfe_flexible_modal_edit_size": false,
                    "acfe_flexible_category": false
                },
                "layout_5f025e12eaf2c": {
                    "key": "layout_5f025e12eaf2c",
                    "name": "testimonials_7",
                    "label": "Testimonials 7",
                    "display": "block",
                    "sub_fields": [
                        {
                            "key": "field_605a7a9014ccd",
                            "label": "Heading",
                            "name": "heading",
                            "type": "clone",
                            "instructions": "",
                            "required": 0,
                            "conditional_logic": 0,
                            "wrapper": {
                                "width": "",
                                "class": "",
                                "id": ""
                            },
                            "acfe_permissions": "",
                            "clone": [
                                "group_5f0df4956b0c7"
                            ],
                            "display": "seamless",
                            "layout": "block",
                            "prefix_label": 0,
                            "prefix_name": 0,
                            "acfe_clone_modal": 0
                        },
                        {
                            "key": "field_605a7a9014cd8",
                            "label": "Testimonials",
                            "name": "testimonials",
                            "type": "clone",
                            "instructions": "",
                            "required": 0,
                            "conditional_logic": 0,
                            "wrapper": {
                                "width": "",
                                "class": "",
                                "id": ""
                            },
                            "acfe_permissions": "",
                            "clone": [
                                "group_5f025cb612228"
                            ],
                            "display": "seamless",
                            "layout": "",
                            "prefix_label": 0,
                            "prefix_name": 0,
                            "acfe_clone_modal": 0
                        }
                    ],
                    "min": "",
                    "max": "",
                    "acfe_flexible_thumbnail": "",
                    "acfe_flexible_render_template": false,
                    "acfe_flexible_render_style": false,
                    "acfe_flexible_render_script": false,
                    "acfe_flexible_settings": false,
                    "acfe_flexible_settings_size": "medium",
                    "acfe_flexible_modal_edit_size": false,
                    "acfe_flexible_category": false
                },
                "layout_5f025e28eaf31": {
                    "key": "layout_5f025e28eaf31",
                    "name": "testimonials_8",
                    "label": "Testimonials 8",
                    "display": "block",
                    "sub_fields": [
                        {
                            "key": "field_605a7a9014ce3",
                            "label": "Testimonials",
                            "name": "testimonials",
                            "type": "clone",
                            "instructions": "",
                            "required": 0,
                            "conditional_logic": 0,
                            "wrapper": {
                                "width": "",
                                "class": "",
                                "id": ""
                            },
                            "acfe_permissions": "",
                            "clone": [
                                "group_5f025cb612228"
                            ],
                            "display": "seamless",
                            "layout": "",
                            "prefix_label": 0,
                            "prefix_name": 0,
                            "acfe_clone_modal": 0
                        }
                    ],
                    "min": "",
                    "max": "",
                    "acfe_flexible_thumbnail": "",
                    "acfe_flexible_render_template": false,
                    "acfe_flexible_render_style": false,
                    "acfe_flexible_render_script": false,
                    "acfe_flexible_settings": false,
                    "acfe_flexible_settings_size": "medium",
                    "acfe_flexible_modal_edit_size": false,
                    "acfe_flexible_category": false
                },
                "layout_5f025e33eaf36": {
                    "key": "layout_5f025e33eaf36",
                    "name": "testimonials_9",
                    "label": "Testimonials 9",
                    "display": "block",
                    "sub_fields": [
                        {
                            "key": "field_605a7a9014cfa",
                            "label": "Heading",
                            "name": "heading",
                            "type": "clone",
                            "instructions": "",
                            "required": 0,
                            "conditional_logic": 0,
                            "wrapper": {
                                "width": "",
                                "class": "",
                                "id": ""
                            },
                            "acfe_permissions": "",
                            "clone": [
                                "group_5f0df4956b0c7"
                            ],
                            "display": "seamless",
                            "layout": "block",
                            "prefix_label": 0,
                            "prefix_name": 0,
                            "acfe_settings": ""
                        },
                        {
                            "key": "field_605a7a9014cef",
                            "label": "Testimonials",
                            "name": "testimonials",
                            "type": "clone",
                            "instructions": "",
                            "required": 0,
                            "conditional_logic": 0,
                            "wrapper": {
                                "width": "",
                                "class": "",
                                "id": ""
                            },
                            "acfe_permissions": "",
                            "clone": [
                                "group_5f025cb612228"
                            ],
                            "display": "seamless",
                            "layout": "",
                            "prefix_label": 0,
                            "prefix_name": 0,
                            "acfe_clone_modal": 0
                        }
                    ],
                    "min": "",
                    "max": "",
                    "acfe_flexible_thumbnail": "",
                    "acfe_flexible_render_template": false,
                    "acfe_flexible_render_style": false,
                    "acfe_flexible_render_script": false,
                    "acfe_flexible_settings": false,
                    "acfe_flexible_settings_size": "medium",
                    "acfe_flexible_modal_edit_size": false,
                    "acfe_flexible_category": false
                },
                "layout_5f025e5deaf3b": {
                    "key": "layout_5f025e5deaf3b",
                    "name": "testimonials_10",
                    "label": "Testimonials 10",
                    "display": "block",
                    "sub_fields": [
                        {
                            "key": "field_605a7a9014d05",
                            "label": "Testimonials",
                            "name": "testimonials",
                            "type": "clone",
                            "instructions": "",
                            "required": 0,
                            "conditional_logic": 0,
                            "wrapper": {
                                "width": "",
                                "class": "",
                                "id": ""
                            },
                            "acfe_permissions": "",
                            "clone": [
                                "group_5f025cb612228"
                            ],
                            "display": "seamless",
                            "layout": "",
                            "prefix_label": 0,
                            "prefix_name": 0,
                            "acfe_clone_modal": 0
                        },
                        {
                            "key": "field_605a7a9014d11",
                            "label": "Excerpt",
                            "name": "excerpt",
                            "type": "clone",
                            "instructions": "",
                            "required": 0,
                            "conditional_logic": 0,
                            "wrapper": {
                                "width": "",
                                "class": "",
                                "id": ""
                            },
                            "acfe_permissions": "",
                            "clone": [
                                "group_5ee94eeb8a826"
                            ],
                            "display": "seamless",
                            "layout": "block",
                            "prefix_label": 0,
                            "prefix_name": 0,
                            "acfe_settings": ""
                        }
                    ],
                    "min": "",
                    "max": "",
                    "acfe_flexible_thumbnail": "",
                    "acfe_flexible_render_template": false,
                    "acfe_flexible_render_style": false,
                    "acfe_flexible_render_script": false,
                    "acfe_flexible_settings": false,
                    "acfe_flexible_settings_size": "medium",
                    "acfe_flexible_modal_edit_size": false,
                    "acfe_flexible_category": false
                },
                "layout_5f028b13911ad": {
                    "key": "layout_5f028b13911ad",
                    "name": "testimonials_11",
                    "label": "Testimonials 11",
                    "display": "block",
                    "sub_fields": [
                        {
                            "key": "field_605a7a9014d1d",
                            "label": "Testimonials",
                            "name": "testimonials",
                            "type": "clone",
                            "instructions": "",
                            "required": 0,
                            "conditional_logic": 0,
                            "wrapper": {
                                "width": "",
                                "class": "",
                                "id": ""
                            },
                            "acfe_permissions": "",
                            "clone": [
                                "group_5f025cb612228"
                            ],
                            "display": "seamless",
                            "layout": "block",
                            "prefix_label": 0,
                            "prefix_name": 0,
                            "acfe_seamless_style": 0,
                            "acfe_clone_modal": 0,
                            "acfe_clone_modal_close": 0,
                            "acfe_clone_modal_button": "",
                            "acfe_clone_modal_size": "large"
                        }
                    ],
                    "min": "",
                    "max": "",
                    "acfe_flexible_thumbnail": "",
                    "acfe_flexible_render_template": false,
                    "acfe_flexible_render_style": false,
                    "acfe_flexible_render_script": false,
                    "acfe_flexible_settings": false,
                    "acfe_flexible_settings_size": "medium",
                    "acfe_flexible_modal_edit_size": false,
                    "acfe_flexible_category": false
                }
            },
            "button_label": "Add Row",
            "min": "",
            "max": 1,
            "acfe_settings": "",
            "acfe_flexible_hide_empty_message": false,
            "acfe_flexible_empty_message": "",
            "acfe_flexible_layouts_previews": false,
            "acfe_flexible_layouts_state": false
        },
        {
            "key": "field_605a7a8f9f91f",
            "label": "Block Options",
            "name": "block_options",
            "type": "clone",
            "instructions": "",
            "required": 0,
            "conditional_logic": 0,
            "wrapper": {
                "width": "",
                "class": "",
                "id": ""
            },
            "acfe_permissions": "",
            "clone": [
                "group_5b69feff3028d"
            ],
            "display": "seamless",
            "layout": "block",
            "prefix_label": 0,
            "prefix_name": 0,
            "acfe_seamless_style": 0,
            "acfe_clone_modal": 0,
            "acfe_clone_modal_close": 0,
            "acfe_clone_modal_button": "",
            "acfe_clone_modal_size": "large",
            "acfe_settings": {
                "acfcloneindex": {
                    "acfe_settings_location": "",
                    "acfe_settings_settings": {
                        "acfcloneindex": {
                            "acfe_settings_setting_type": "required",
                            "acfe_settings_setting_name": "",
                            "acfe_settings_setting_operator": "true",
                            "acfe_settings_setting_value": ""
                        }
                    }
                }
            }
        }
    ],
    "location": [
        [
            {
                "param": "post_type",
                "operator": "==",
                "value": "post"
            }
        ]
    ],
    "menu_order": 0,
    "position": "acf_after_title",
    "style": "seamless",
    "label_placement": "left",
    "instruction_placement": "label",
    "hide_on_screen": "",
    "active": false,
    "description": "",
    "show_in_rest": 0,
    "acfe_display_title": "Block: Testimonials",
    "acfe_autosync": [
        "json"
    ],
    "acfe_permissions": "",
    "acfe_form": 1,
    "acfe_meta": "",
    "acfe_note": "",
    "modified": 1642118900
}